excelmustdie
