Metadata-Version: 1.1
Name: excelmustdie
Version: 0.4.2
Summary: A MIPT lab report creation tool
Home-page: UNKNOWN
Author: Andrei Pago
Author-email: andpago@gmail.com
License: MIT
Keywords: MIPT tex excel
Platform: UNKNOWN
Classifier: License :: OSI Approved :: MIT License
Classifier: Programming Language :: Python :: 3.6
